[
    {
        "ABCInfo": {
            "Enable": "true",
            "StationId": "1",
            "StationName": "RcamMic2",
            "TraceLineId": "Line11",
            "TraceSoftName": "Soft1",
            "TraceStationId": "ST1",
            "TraceURL": "URL1",
            "UploadRecipe": "1"
        },
        "Axis": {
            "Servo": [
                {
                    "axisId": "0",
                    "axisType": "Y",
                    "cardId": "1001",
                    "division": "6553.6"
                },
                {
                    "axisId": "1",
                    "axisType": "Z1",
                    "cardId": "1001",
                    "division": "32768"
                }
            ]
        },
        "Device": [
            {
                "connectParam": "192.168.1.101",
                "deviceType": "F28Light",
                "measureInfo": [
                    {
                        "itemName": "Rcam",
                        "paramId": "St1Dev1Test1",
                        "traceName": "rcam",
                        "uiName": "Rcam"
                    }
                ],
                "testFlow": "0"
            },
            {
                "connectParam": "192.168.1.102",
                "deviceType": "F28Light",
                "measureInfo": [
                    {
                        "itemName": "Mic2",
                        "paramId": "St1Dev2Test1",
                        "traceName": "Mic2",
                        "uiName": "Mic2"
                    }
                ],
                "testFlow": "0"
            }
        ],
        "SealInfo": [
            {
                "limit": "8500",
                "name": "密封圈1"
            },
            {
                "limit": "8500",
                "name": "密封圈2"
            }
        ]
    },
    {
        "ABCInfo": {
            "Enable": "true",
            "StationId": "2",
            "StationName": "RcamMic2",
            "TraceLineId": "Line11",
            "TraceSoftName": "Soft1",
            "TraceStationId": "ST1",
            "TraceURL": "URL1",
            "UploadRecipe": "1"
        },
        "Axis": {
            "Servo": [
                {
                    "axisId": "2",
                    "axisType": "Y",
                    "cardId": "1001",
                    "division": "6553.6"
                },
                {
                    "axisId": "3",
                    "axisType": "Z1",
                    "cardId": "1001",
                    "division": "32768"
                }
            ]
        },
        "Device": [
            {
                "connectParam": "192.168.1.103",
                "deviceType": "F28Light",
                "measureInfo": [
                    {
                        "itemName": "Rcam",
                        "paramId": "St2Dev1Test1",
                        "traceName": "rcam",
                        "uiName": "Rcam"
                    }
                ],
                "testFlow": "0"
            },
            {
                "connectParam": "192.168.1.104",
                "deviceType": "F28Light",
                "measureInfo": [
                    {
                        "itemName": "Mic2",
                        "paramId": "St2Dev2Test1",
                        "traceName": "Mic2",
                        "uiName": "Mic2"
                    }
                ],
                "testFlow": "0"
            }
        ],
        "SealInfo": [
            {
                "limit": "8500",
                "name": "密封圈1"
            },
            {
                "limit": "8500",
                "name": "密封圈2"
            }
        ]
    },
    {
        "ABCInfo": {
            "Enable": "true",
            "StationId": "3",
            "StationName": "RcamMic2",
            "TraceLineId": "Line11",
            "TraceSoftName": "Soft1",
            "TraceStationId": "ST1",
            "TraceURL": "URL1",
            "UploadRecipe": "1"
        },
        "Axis": {
            "Servo": [
                {
                    "axisId": "4",
                    "axisType": "Y",
                    "cardId": "1001",
                    "division": "6553.6"
                },
                {
                    "axisId": "5",
                    "axisType": "Z1",
                    "cardId": "1001",
                    "division": "32768"
                }
            ]
        },
        "Device": [
            {
                "connectParam": "192.168.1.105",
                "deviceType": "F28Light",
                "measureInfo": [
                    {
                        "itemName": "Rcam",
                        "paramId": "St3Dev1Test1",
                        "traceName": "rcam",
                        "uiName": "Rcam"
                    }
                ],
                "testFlow": "0"
            },
            {
                "connectParam": "192.168.1.106",
                "deviceType": "F28Light",
                "measureInfo": [
                    {
                        "itemName": "Mic2",
                        "paramId": "St3Dev2Test1",
                        "traceName": "Mic2",
                        "uiName": "Mic2"
                    }
                ],
                "testFlow": "0"
            }
        ],
        "SealInfo": [
            {
                "limit": "2500",
                "name": "8500"
            },
            {
                "limit": "2500",
                "name": "8500"
            }
        ]
    },
    {
        "ABCInfo": {
            "Enable": "true",
            "StationId": "4",
            "StationName": "RcamMic2",
            "TraceLineId": "Line11",
            "TraceSoftName": "Soft1",
            "TraceStationId": "ST1",
            "TraceURL": "URL1",
            "UploadRecipe": "1"
        },
        "Axis": {
            "Servo": [
                {
                    "axisId": "6",
                    "axisType": "Y",
                    "cardId": "1001",
                    "division": "6553.6"
                },
                {
                    "axisId": "7",
                    "axisType": "Z1",
                    "cardId": "1001",
                    "division": "32768"
                }
            ]
        },
        "Device": [
            {
                "connectParam": "192.168.1.107",
                "deviceType": "F28Light",
                "measureInfo": [
                    {
                        "itemName": "Rcam",
                        "paramId": "St4Dev1Test1",
                        "traceName": "rcam",
                        "uiName": "Rcam"
                    }
                ],
                "testFlow": "0"
            },
            {
                "connectParam": "192.168.1.108",
                "deviceType": "F28Light",
                "measureInfo": [
                    {
                        "itemName": "Mic2",
                        "paramId": "St4Dev2Test1",
                        "traceName": "Mic2",
                        "uiName": "Mic2"
                    }
                ],
                "testFlow": "0"
            }
        ],
        "SealInfo": [
            {
                "limit": "8500",
                "name": "密封圈1"
            },
            {
                "limit": "8500",
                "name": "密封圈2"
            }
        ]
    },
    {
        "ABCInfo": {
            "Enable": "true",
            "StationId": "5",
            "StationName": "RcamMic2",
            "TraceLineId": "Line11",
            "TraceSoftName": "Soft1",
            "TraceStationId": "ST1",
            "TraceURL": "URL1",
            "UploadRecipe": "1"
        },
        "Axis": {
            "Servo": [
                {
                    "axisId": "8",
                    "axisType": "Y",
                    "cardId": "1001",
                    "division": "6553.6"
                },
                {
                    "axisId": "9",
                    "axisType": "Z1",
                    "cardId": "1001",
                    "division": "32768"
                }
            ]
        },
        "Device": [
            {
                "connectParam": "192.168.1.109",
                "deviceType": "F28Light",
                "measureInfo": [
                    {
                        "itemName": "Rcam",
                        "paramId": "St5Dev1Test1",
                        "traceName": "rcam",
                        "uiName": "Rcam"
                    }
                ],
                "testFlow": "0"
            },
            {
                "connectParam": "192.168.1.110",
                "deviceType": "F28Light",
                "measureInfo": [
                    {
                        "itemName": "Mic2",
                        "paramId": "St5Dev2Test1",
                        "traceName": "Mic2",
                        "uiName": "Mic2"
                    }
                ],
                "testFlow": "0"
            }
        ],
        "SealInfo": [
            {
                "limit": "8500",
                "name": "密封圈1"
            },
            {
                "limit": "8500",
                "name": "密封圈2"
            }
        ]
    },
    {
        "ABCInfo": {
            "Enable": "true",
            "StationId": "6",
            "StationName": "RcamMic2",
            "TraceLineId": "Line11",
            "TraceSoftName": "Soft1",
            "TraceStationId": "ST1",
            "TraceURL": "URL1",
            "UploadRecipe": "1"
        },
        "Axis": {
            "Servo": [
                {
                    "axisId": "10",
                    "axisType": "Y",
                    "cardId": "1001",
                    "division": "6553.6"
                },
                {
                    "axisId": "11",
                    "axisType": "Z1",
                    "cardId": "1001",
                    "division": "32768"
                }
            ]
        },
        "Device": [
            {
                "connectParam": "192.168.1.111",
                "deviceType": "F28Light",
                "measureInfo": [
                    {
                        "itemName": "Rcam",
                        "paramId": "St6Dev1Test1",
                        "traceName": "rcam",
                        "uiName": "Rcam"
                    }
                ],
                "testFlow": "0"
            },
            {
                "connectParam": "192.168.1.112",
                "deviceType": "F28Light",
                "measureInfo": [
                    {
                        "itemName": "Mic2",
                        "paramId": "St6Dev2Test1",
                        "traceName": "Mic2",
                        "uiName": "Mic2"
                    }
                ],
                "testFlow": "0"
            }
        ],
        "SealInfo": [
            {
                "limit": "8500",
                "name": "密封圈1"
            },
            {
                "limit": "8500",
                "name": "密封圈2"
            }
        ]
    }
]
